Metadata-Version: 1.0
Name: mplsvds
Version: 0.1.7
Summary: matplotlib styling for svds
Home-page: UNKNOWN
Author: Daniel Margala, Jonathan Whitmore
Author-email: daniel@svds.com, jonathan@svds.com
License: UNKNOWN
Platform: UNKNOWN
